DiffRed/__init__.py
DiffRed/main.py
DiffRed/utils.py
diffred-0.1.3.dist-info/METADATA
diffred-0.1.3.dist-info/WHEEL
diffred-0.1.3.dist-info/top_level.txt
diffred-0.1.3.dist-info/RECORD
