Metadata-Version: 2.1
Name: diffred
Version: 0.1.3
Summary: Official Implementation of "DiffRed: Dimensionality Reduction guided by stable rank"
Home-page: https://github.com/S3-Lab-IIT/DiffRed/tree/master
Download-URL: https://github.com/S3-Lab-IIT/DiffRed/archive/refs/tags/v0.1.0.tar.gz
Author: Prarabdh Shukla
Author-email: prarabdh.10@gmail.com
Project-URL: Homepage, https://github.com/S3-Lab-IIT/DiffRed/tree/master
Requires-Dist: gensim ==4.3.2
Requires-Dist: kaggle ==1.5.16
Requires-Dist: matplotlib ==3.7.2
Requires-Dist: MulticoreTSNE ==0.1
Requires-Dist: nltk ==3.8.1
Requires-Dist: numba ==0.57.1
Requires-Dist: numpy ==1.24.4
Requires-Dist: opencv-python ==4.8.1.78
Requires-Dist: openpyxl ==3.1.2
Requires-Dist: pandas ==2.2.1
Requires-Dist: Requests ==2.31.0
Requires-Dist: scikit-learn ==1.3.0
Requires-Dist: share-array-widmi ==0.0.1
Requires-Dist: tensorflow ==2.14.0
Requires-Dist: tqdm ==4.66.1
Requires-Dist: tsnecuda ==3.0.2
Requires-Dist: umap-learn ==0.5.3
